e80analysis/__init__.py
e80analysis/e80data.json
e80analysis-0.1.dist-info/METADATA
e80analysis-0.1.dist-info/RECORD
e80analysis-0.1.dist-info/WHEEL
e80analysis-0.1.dist-info/top_level.txt
