Metadata-Version: 2.1
Name: e80analysis
Version: 0.1
Summary: A tool to find the equivalent Cooper E-loading for a user-specified train configuration.
Home-page: https://github.com/rspears74/e80analysis
Author: Randall Spears
Author-email: rspears690@gmail.com
License: MIT
Platform: UNKNOWN
Requires-Dist: matplotlib
